deep_serialization/__init__.py
deep_serialization/deep_serialization.py
deep_serialization/example.py
deep_serialization/json_converter.py
deep_serialization/memory_objects.py
deep_serialization/test_json.json
deep_serialization/utils.py
deep_serialization-1.0.0.dist-info/entry_points.txt
deep_serialization-1.0.0.dist-info/LICENSE
deep_serialization-1.0.0.dist-info/WHEEL
deep_serialization-1.0.0.dist-info/METADATA
deep_serialization-1.0.0.dist-info/RECORD
