Metadata-Version: 2.1
Name: deep-serialization
Version: 1.0.0
Summary: Automatic python objects JSON serialization
Author: Vyacheslav Tamarin
Author-email: vyacheslav.tamarin@yandex.ru
Requires-Python: >=3.6,<4.0
Classifier: Programming Language :: Python :: 3
Classifier: Programming Language :: Python :: 3.6
Classifier: Programming Language :: Python :: 3.7
Classifier: Programming Language :: Python :: 3.8
Classifier: Programming Language :: Python :: 3.9
Classifier: Programming Language :: Python :: 3.10
